dataflow_sdk/__init__.py
dataflow_sdk/entity/__init__.py
dataflow_sdk/entity/client.py
dataflow_sdk/entity/model.py
dataflow_sdk/entity/result.py
dataflow_sdk/entity/utils.py
dataflow_sdk/libs/__init__.py
dataflow_sdk/libs/protobuf/__init__.py
dataflow_sdk/libs/protobuf/google/__init__.py
dataflow_sdk/libs/protobuf/google/api/__init__.py
dataflow_sdk/libs/protobuf/google/api/annotations_pb2.py
dataflow_sdk/libs/protobuf/google/api/annotations_pb2_grpc.py
dataflow_sdk/libs/protobuf/google/api/field_behavior_pb2.py
dataflow_sdk/libs/protobuf/google/api/field_behavior_pb2_grpc.py
dataflow_sdk/libs/protobuf/google/api/http_pb2.py
dataflow_sdk/libs/protobuf/google/api/http_pb2_grpc.py
dataflow_sdk/libs/sink/__init__.py
dataflow_sdk/libs/sink/sink_pb2.py
dataflow_sdk/libs/sink/sink_pb2.pyi
dataflow_sdk/libs/sink/sink_pb2_grpc.py
dataflow_sdk-0.2.2.dist-info/METADATA
dataflow_sdk-0.2.2.dist-info/WHEEL
dataflow_sdk-0.2.2.dist-info/top_level.txt
dataflow_sdk-0.2.2.dist-info/RECORD
