Metadata-Version: 2.4
Name: dataflow-sdk
Version: 0.2.2
Summary: Add your description here
Requires-Python: >=3.13
Requires-Dist: grpcio>=1.76.0
Requires-Dist: loguru>=0.7.3
Requires-Dist: orjson>=3.11.5
Requires-Dist: protobuf>=6.33.2
Requires-Dist: pydantic>=2.12.5
